[{"batter":"SD Hope","total_runs":481,"matches":12,"dismissals":9,"average":53.44,"balls_faced":343,"SR":140.23,"team":"Guyana Amazon Warriors"},{"batter":"Saim Ayub","total_runs":478,"matches":13,"dismissals":12,"average":39.83,"balls_faced":336,"SR":142.26,"team":"Guyana Amazon Warriors"},{"batter":"Imad Wasim","total_runs":313,"matches":10,"dismissals":10,"average":31.3,"balls_faced":241,"SR":129.88,"team":"Jamaica Tallawahs"},{"batter":"N Pooran","total_runs":291,"matches":10,"dismissals":9,"average":32.33,"balls_faced":187,"SR":155.61,"team":"Trinbago Knight Riders"},{"batter":"BA King","total_runs":288,"matches":10,"dismissals":10,"average":28.8,"balls_faced":198,"SR":145.45,"team":"Jamaica Tallawahs"},{"batter":"ADS Fletcher","total_runs":278,"matches":8,"dismissals":8,"average":34.75,"balls_faced":193,"SR":144.04,"team":"St Kitts and Nevis Patriots"},{"batter":"MJ Guptill","total_runs":262,"matches":10,"dismissals":7,"average":37.43,"balls_faced":227,"SR":115.42,"team":"Trinbago Knight Riders"},{"batter":"J Charles","total_runs":238,"matches":8,"dismissals":9,"average":26.44,"balls_faced":191,"SR":124.61,"team":"Saint Lucia Kings"},{"batter":"SO Hetmyer","total_runs":227,"matches":10,"dismissals":9,"average":25.22,"balls_faced":164,"SR":138.41,"team":"Guyana Amazon Warriors"},{"batter":"Azam Khan","total_runs":224,"matches":12,"dismissals":11,"average":20.36,"balls_faced":144,"SR":155.56,"team":"Guyana Amazon Warriors"},{"batter":"M Deyal","total_runs":224,"matches":10,"dismissals":9,"average":24.89,"balls_faced":155,"SR":144.52,"team":"Trinbago Knight Riders"},{"batter":"AD Hales","total_runs":217,"matches":7,"dismissals":6,"average":36.17,"balls_faced":148,"SR":146.62,"team":"Jamaica Tallawahs"},{"batter":"KA Pollard","total_runs":215,"matches":10,"dismissals":9,"average":23.89,"balls_faced":139,"SR":154.68,"team":"Trinbago Knight Riders"},{"batter":"SE Rutherford","total_runs":194,"matches":8,"dismissals":7,"average":27.71,"balls_faced":125,"SR":155.2,"team":"St Kitts and Nevis Patriots"},{"batter":"RRS Cornwall","total_runs":193,"matches":9,"dismissals":8,"average":24.12,"balls_faced":111,"SR":173.87,"team":"Barbados Royals"},{"batter":"R Powell","total_runs":193,"matches":9,"dismissals":7,"average":27.57,"balls_faced":114,"SR":169.3,"team":"Barbados Royals"},{"batter":"SSJ Brooks","total_runs":186,"matches":11,"dismissals":10,"average":18.6,"balls_faced":143,"SR":130.07,"team":"Jamaica Tallawahs"},{"batter":"C Munro","total_runs":175,"matches":6,"dismissals":5,"average":35.0,"balls_faced":145,"SR":120.69,"team":"Saint Lucia Kings"},{"batter":"KMA Paul","total_runs":175,"matches":6,"dismissals":5,"average":35.0,"balls_faced":112,"SR":156.25,"team":"Guyana Amazon Warriors"},{"batter":"A Athanaze","total_runs":165,"matches":8,"dismissals":7,"average":23.57,"balls_faced":152,"SR":108.55,"team":"Barbados Royals"},{"batter":"KR Mayers","total_runs":159,"matches":8,"dismissals":8,"average":19.88,"balls_faced":117,"SR":135.9,"team":"Barbados Royals"},{"batter":"RL Chase","total_runs":156,"matches":8,"dismissals":7,"average":22.29,"balls_faced":125,"SR":124.8,"team":"Saint Lucia Kings"},{"batter":"FA Allen","total_runs":152,"matches":9,"dismissals":8,"average":19.0,"balls_faced":97,"SR":156.7,"team":"Jamaica Tallawahs"},{"batter":"L Tucker","total_runs":150,"matches":5,"dismissals":4,"average":37.5,"balls_faced":121,"SR":123.97,"team":"Trinbago Knight Riders"},{"batter":"RA Reifer","total_runs":146,"matches":9,"dismissals":6,"average":24.33,"balls_faced":142,"SR":102.82,"team":"Jamaica Tallawahs"},{"batter":"AD Russell","total_runs":145,"matches":10,"dismissals":6,"average":24.17,"balls_faced":90,"SR":161.11,"team":"Trinbago Knight Riders"},{"batter":"Sikandar Raza","total_runs":141,"matches":9,"dismissals":8,"average":17.62,"balls_faced":105,"SR":134.29,"team":"Saint Lucia Kings"},{"batter":"PBB Rajapaksa","total_runs":137,"matches":4,"dismissals":4,"average":34.25,"balls_faced":99,"SR":138.38,"team":"Saint Lucia Kings"},{"batter":"LJ Evans","total_runs":136,"matches":7,"dismissals":7,"average":19.43,"balls_faced":110,"SR":123.64,"team":"Barbados Royals"},{"batter":"C Bosch","total_runs":130,"matches":8,"dismissals":8,"average":16.25,"balls_faced":107,"SR":121.5,"team":"St Kitts and Nevis Patriots"},{"batter":"SC Williams","total_runs":125,"matches":8,"dismissals":4,"average":31.25,"balls_faced":89,"SR":140.45,"team":"Saint Lucia Kings"},{"batter":"CAK Walton","total_runs":122,"matches":6,"dismissals":4,"average":30.5,"balls_faced":109,"SR":111.93,"team":"Trinbago Knight Riders"},{"batter":"R Shepherd","total_runs":113,"matches":8,"dismissals":3,"average":37.67,"balls_faced":48,"SR":235.42,"team":"Guyana Amazon Warriors"},{"batter":"F du Plessis","total_runs":112,"matches":3,"dismissals":3,"average":37.33,"balls_faced":76,"SR":147.37,"team":"Saint Lucia Kings"},{"batter":"JO Holder","total_runs":106,"matches":8,"dismissals":7,"average":15.14,"balls_faced":86,"SR":123.26,"team":"Barbados Royals"},{"batter":"RS Primus","total_runs":95,"matches":7,"dismissals":5,"average":19.0,"balls_faced":71,"SR":133.8,"team":"Saint Lucia Kings"},{"batter":"OF Smith","total_runs":89,"matches":7,"dismissals":4,"average":22.25,"balls_faced":71,"SR":125.35,"team":"Guyana Amazon Warriors"},{"batter":"E Lewis","total_runs":85,"matches":7,"dismissals":7,"average":12.14,"balls_faced":67,"SR":126.87,"team":"St Kitts and Nevis Patriots"},{"batter":"WCF Smeed","total_runs":80,"matches":4,"dismissals":4,"average":20.0,"balls_faced":59,"SR":135.59,"team":"St Kitts and Nevis Patriots"},{"batter":"NRJ Young","total_runs":76,"matches":5,"dismissals":4,"average":19.0,"balls_faced":86,"SR":88.37,"team":"Barbados Royals"},{"batter":"D Pretorius","total_runs":76,"matches":8,"dismissals":6,"average":12.67,"balls_faced":61,"SR":124.59,"team":"Guyana Amazon Warriors"},{"batter":"CJ Green","total_runs":72,"matches":7,"dismissals":6,"average":12.0,"balls_faced":43,"SR":167.44,"team":"Jamaica Tallawahs"},{"batter":"KSA McKenzie","total_runs":72,"matches":7,"dismissals":7,"average":10.29,"balls_faced":88,"SR":81.82,"team":"Jamaica Tallawahs"},{"batter":"J Da Silva","total_runs":69,"matches":4,"dismissals":3,"average":23.0,"balls_faced":63,"SR":109.52,"team":"St Kitts and Nevis Patriots"},{"batter":"DC Drakes","total_runs":68,"matches":6,"dismissals":2,"average":34.0,"balls_faced":62,"SR":109.68,"team":"St Kitts and Nevis Patriots"},{"batter":"AJ Hosein","total_runs":63,"matches":6,"dismissals":5,"average":12.6,"balls_faced":59,"SR":106.78,"team":"Trinbago Knight Riders"}]