{"name":"TS Mills","competition":"sa20","batting":{"total_runs":8,"matches":2,"innings":2,"dismissals":1,"average":8.0,"sr":114.29,"highest":7,"fifties":0,"hundreds":0},"innings_list":[{"inning_num":1,"runs":7,"dismissed":true},{"inning_num":2,"runs":1,"dismissed":false}],"batting_seasons":[{"season":2025,"runs":8,"matches":2,"dismissals":1,"avg":8.0}],"bowling":{"wickets":5,"matches":4,"balls":82,"runs_conceded":107,"economy":7.83,"average":21.4},"bowling_seasons":[{"season":2025,"runs":74,"wickets":5,"balls":62,"matches":3,"economy":7.16},{"season":2026,"runs":33,"wickets":0,"balls":20,"matches":1,"economy":9.9}]}