{"name":"Abu Hider","competition":"bpl","batting":{"total_runs":258,"matches":39,"innings":39,"dismissals":22,"average":11.73,"sr":107.5,"highest":28,"fifties":0,"hundreds":0},"innings_list":[{"inning_num":1,"runs":18,"dismissed":false},{"inning_num":2,"runs":1,"dismissed":false},{"inning_num":3,"runs":0,"dismissed":true},{"inning_num":4,"runs":2,"dismissed":false},{"inning_num":5,"runs":9,"dismissed":true},{"inning_num":6,"runs":16,"dismissed":false},{"inning_num":7,"runs":7,"dismissed":false},{"inning_num":8,"runs":2,"dismissed":false},{"inning_num":9,"runs":0,"dismissed":true},{"inning_num":10,"runs":0,"dismissed":true},{"inning_num":11,"runs":5,"dismissed":false},{"inning_num":12,"runs":9,"dismissed":false},{"inning_num":13,"runs":5,"dismissed":true},{"inning_num":14,"runs":0,"dismissed":true},{"inning_num":15,"runs":6,"dismissed":true},{"inning_num":16,"runs":0,"dismissed":true},{"inning_num":17,"runs":28,"dismissed":false},{"inning_num":18,"runs":12,"dismissed":false},{"inning_num":19,"runs":7,"dismissed":true},{"inning_num":20,"runs":0,"dismissed":true},{"inning_num":21,"runs":3,"dismissed":true},{"inning_num":22,"runs":6,"dismissed":false},{"inning_num":23,"runs":1,"dismissed":false},{"inning_num":24,"runs":19,"dismissed":true},{"inning_num":25,"runs":7,"dismissed":false},{"inning_num":26,"runs":11,"dismissed":false},{"inning_num":27,"runs":0,"dismissed":true},{"inning_num":28,"runs":7,"dismissed":true},{"inning_num":29,"runs":12,"dismissed":false},{"inning_num":30,"runs":21,"dismissed":false},{"inning_num":31,"runs":4,"dismissed":true},{"inning_num":32,"runs":14,"dismissed":true},{"inning_num":33,"runs":0,"dismissed":true},{"inning_num":34,"runs":0,"dismissed":true},{"inning_num":35,"runs":1,"dismissed":false},{"inning_num":36,"runs":4,"dismissed":true},{"inning_num":37,"runs":13,"dismissed":true},{"inning_num":38,"runs":1,"dismissed":true},{"inning_num":39,"runs":7,"dismissed":true}],"batting_seasons":[{"season":2015,"runs":19,"matches":2,"dismissals":0,"avg":NaN},{"season":2016,"runs":27,"matches":4,"dismissals":2,"avg":13.5},{"season":2017,"runs":23,"matches":6,"dismissals":2,"avg":11.5},{"season":2019,"runs":51,"matches":6,"dismissals":4,"avg":12.75},{"season":2020,"runs":10,"matches":3,"dismissals":3,"avg":3.33},{"season":2022,"runs":26,"matches":3,"dismissals":1,"avg":26.0},{"season":2023,"runs":18,"matches":2,"dismissals":0,"avg":NaN},{"season":2024,"runs":19,"matches":3,"dismissals":2,"avg":9.5},{"season":2025,"runs":57,"matches":8,"dismissals":6,"avg":9.5},{"season":2026,"runs":8,"matches":2,"dismissals":2,"avg":4.0}],"bowling":{"wickets":81,"matches":76,"balls":1447,"runs_conceded":1926,"economy":7.99,"average":23.78},"bowling_seasons":[{"season":2015,"runs":272,"wickets":20,"balls":250,"matches":11,"economy":6.53},{"season":2016,"runs":212,"wickets":4,"balls":150,"matches":7,"economy":8.48},{"season":2017,"runs":293,"wickets":15,"balls":236,"matches":13,"economy":7.45},{"season":2019,"runs":275,"wickets":5,"balls":191,"matches":12,"economy":8.64},{"season":2020,"runs":108,"wickets":0,"balls":66,"matches":4,"economy":9.82},{"season":2022,"runs":116,"wickets":4,"balls":78,"matches":5,"economy":8.92},{"season":2023,"runs":77,"wickets":3,"balls":72,"matches":4,"economy":6.42},{"season":2024,"runs":133,"wickets":13,"balls":106,"matches":6,"economy":7.53},{"season":2025,"runs":333,"wickets":14,"balls":220,"matches":10,"economy":9.08},{"season":2026,"runs":107,"wickets":3,"balls":78,"matches":4,"economy":8.23}],"cais_batting":{"score":197.24,"rank":101,"total":160},"cais_bowling":{"score":23.58,"rank":57,"total":139}}