{"name":"Sabbir Hossain","competition":"bpl","batting":{"total_runs":127,"matches":13,"innings":13,"dismissals":13,"average":9.77,"sr":102.42,"highest":39,"fifties":0,"hundreds":0},"innings_list":[{"inning_num":1,"runs":1,"dismissed":true},{"inning_num":2,"runs":4,"dismissed":true},{"inning_num":3,"runs":5,"dismissed":true},{"inning_num":4,"runs":0,"dismissed":true},{"inning_num":5,"runs":8,"dismissed":true},{"inning_num":6,"runs":11,"dismissed":true},{"inning_num":7,"runs":39,"dismissed":true},{"inning_num":8,"runs":11,"dismissed":true},{"inning_num":9,"runs":0,"dismissed":true},{"inning_num":10,"runs":5,"dismissed":true},{"inning_num":11,"runs":15,"dismissed":true},{"inning_num":12,"runs":6,"dismissed":true},{"inning_num":13,"runs":22,"dismissed":true}],"batting_seasons":[{"season":2024,"runs":10,"matches":4,"dismissals":4,"avg":2.5},{"season":2025,"runs":95,"matches":8,"dismissals":8,"avg":11.88},{"season":2026,"runs":22,"matches":1,"dismissals":1,"avg":22.0}],"bowling":{"wickets":5,"matches":11,"balls":102,"runs_conceded":178,"economy":10.47,"average":35.6},"bowling_seasons":[{"season":2024,"runs":37,"wickets":1,"balls":24,"matches":3,"economy":9.25},{"season":2025,"runs":94,"wickets":3,"balls":48,"matches":6,"economy":11.75},{"season":2026,"runs":47,"wickets":1,"balls":30,"matches":2,"economy":9.4}]}