{"name":"Nasir Jamshed","competition":"t20is","batting":{"total_runs":363,"matches":18,"innings":18,"dismissals":17,"average":21.35,"sr":113.44,"highest":56,"fifties":2,"hundreds":0},"innings_list":[{"inning_num":1,"runs":10,"dismissed":true},{"inning_num":2,"runs":45,"dismissed":true},{"inning_num":3,"runs":17,"dismissed":true},{"inning_num":4,"runs":56,"dismissed":true},{"inning_num":5,"runs":29,"dismissed":false},{"inning_num":6,"runs":0,"dismissed":true},{"inning_num":7,"runs":4,"dismissed":true},{"inning_num":8,"runs":55,"dismissed":true},{"inning_num":9,"runs":4,"dismissed":true},{"inning_num":10,"runs":2,"dismissed":true},{"inning_num":11,"runs":41,"dismissed":true},{"inning_num":12,"runs":13,"dismissed":true},{"inning_num":13,"runs":6,"dismissed":true},{"inning_num":14,"runs":2,"dismissed":true},{"inning_num":15,"runs":23,"dismissed":true},{"inning_num":16,"runs":19,"dismissed":true},{"inning_num":17,"runs":18,"dismissed":true},{"inning_num":18,"runs":19,"dismissed":true}],"batting_seasons":[{"season":2012,"runs":263,"matches":11,"dismissals":10,"avg":26.3},{"season":2013,"runs":100,"matches":7,"dismissals":7,"avg":14.29}],"cais_batting":{"score":170.18,"rank":281,"total":315}}