{"name":"CJ Green","competition":"ntb","batting":{"total_runs":659,"matches":41,"innings":41,"dismissals":27,"average":24.41,"sr":147.1,"highest":46,"fifties":0,"hundreds":0},"innings_list":[{"inning_num":1,"runs":6,"dismissed":true},{"inning_num":2,"runs":0,"dismissed":true},{"inning_num":3,"runs":7,"dismissed":false},{"inning_num":4,"runs":23,"dismissed":false},{"inning_num":5,"runs":4,"dismissed":true},{"inning_num":6,"runs":19,"dismissed":true},{"inning_num":7,"runs":16,"dismissed":true},{"inning_num":8,"runs":26,"dismissed":true},{"inning_num":9,"runs":13,"dismissed":false},{"inning_num":10,"runs":18,"dismissed":true},{"inning_num":11,"runs":15,"dismissed":false},{"inning_num":12,"runs":16,"dismissed":true},{"inning_num":13,"runs":8,"dismissed":false},{"inning_num":14,"runs":3,"dismissed":false},{"inning_num":15,"runs":22,"dismissed":true},{"inning_num":16,"runs":4,"dismissed":true},{"inning_num":17,"runs":7,"dismissed":true},{"inning_num":18,"runs":46,"dismissed":false},{"inning_num":19,"runs":2,"dismissed":true},{"inning_num":20,"runs":14,"dismissed":true},{"inning_num":21,"runs":7,"dismissed":true},{"inning_num":22,"runs":4,"dismissed":true},{"inning_num":23,"runs":44,"dismissed":false},{"inning_num":24,"runs":31,"dismissed":false},{"inning_num":25,"runs":22,"dismissed":false},{"inning_num":26,"runs":17,"dismissed":true},{"inning_num":27,"runs":15,"dismissed":true},{"inning_num":28,"runs":38,"dismissed":true},{"inning_num":29,"runs":3,"dismissed":true},{"inning_num":30,"runs":24,"dismissed":true},{"inning_num":31,"runs":5,"dismissed":true},{"inning_num":32,"runs":0,"dismissed":true},{"inning_num":33,"runs":15,"dismissed":false},{"inning_num":34,"runs":36,"dismissed":false},{"inning_num":35,"runs":15,"dismissed":true},{"inning_num":36,"runs":6,"dismissed":true},{"inning_num":37,"runs":26,"dismissed":true},{"inning_num":38,"runs":6,"dismissed":false},{"inning_num":39,"runs":31,"dismissed":false},{"inning_num":40,"runs":16,"dismissed":true},{"inning_num":41,"runs":29,"dismissed":true}],"batting_seasons":[{"season":2019,"runs":40,"matches":5,"dismissals":3,"avg":13.33},{"season":2021,"runs":107,"matches":6,"dismissals":4,"avg":26.75},{"season":2022,"runs":177,"matches":12,"dismissals":8,"avg":22.12},{"season":2024,"runs":155,"matches":8,"dismissals":7,"avg":22.14},{"season":2025,"runs":180,"matches":10,"dismissals":6,"avg":30.0}],"bowling":{"wickets":61,"matches":52,"balls":1116,"runs_conceded":1388,"economy":7.46,"average":22.75},"bowling_seasons":[{"season":2019,"runs":140,"wickets":5,"balls":130,"matches":6,"economy":6.46},{"season":2021,"runs":221,"wickets":9,"balls":150,"matches":7,"economy":8.84},{"season":2022,"runs":369,"wickets":14,"balls":280,"matches":14,"economy":7.91},{"season":2024,"runs":281,"wickets":14,"balls":238,"matches":11,"economy":7.08},{"season":2025,"runs":377,"wickets":19,"balls":318,"matches":14,"economy":7.11}],"cais_batting":{"score":281.68,"rank":23,"total":401},"cais_bowling":{"score":27.17,"rank":167,"total":380}}