{"name":"TE Bailey","competition":"ntb","batting":{"total_runs":27,"matches":8,"innings":8,"dismissals":6,"average":4.5,"sr":93.1,"highest":10,"fifties":0,"hundreds":0},"innings_list":[{"inning_num":1,"runs":0,"dismissed":true},{"inning_num":2,"runs":8,"dismissed":true},{"inning_num":3,"runs":10,"dismissed":true},{"inning_num":4,"runs":3,"dismissed":true},{"inning_num":5,"runs":0,"dismissed":true},{"inning_num":6,"runs":3,"dismissed":false},{"inning_num":7,"runs":0,"dismissed":true},{"inning_num":8,"runs":3,"dismissed":false}],"batting_seasons":[{"season":2015,"runs":0,"matches":1,"dismissals":1,"avg":0.0},{"season":2017,"runs":18,"matches":2,"dismissals":2,"avg":9.0},{"season":2021,"runs":3,"matches":2,"dismissals":2,"avg":1.5},{"season":2023,"runs":6,"matches":3,"dismissals":1,"avg":6.0}],"bowling":{"wickets":35,"matches":34,"balls":533,"runs_conceded":804,"economy":9.05,"average":22.97},"bowling_seasons":[{"season":2015,"runs":251,"wickets":8,"balls":140,"matches":9,"economy":10.76},{"season":2017,"runs":105,"wickets":4,"balls":79,"matches":4,"economy":7.97},{"season":2020,"runs":109,"wickets":12,"balls":96,"matches":6,"economy":6.81},{"season":2021,"runs":125,"wickets":4,"balls":67,"matches":5,"economy":11.19},{"season":2022,"runs":58,"wickets":1,"balls":43,"matches":3,"economy":8.09},{"season":2023,"runs":156,"wickets":6,"balls":108,"matches":7,"economy":8.67}],"cais_bowling":{"score":32.52,"rank":102,"total":387}}