{"name":"WMH Rhodes","competition":"ntb","batting":{"total_runs":944,"matches":58,"innings":58,"dismissals":44,"average":21.45,"sr":126.2,"highest":79,"fifties":3,"hundreds":0},"innings_list":[{"inning_num":1,"runs":11,"dismissed":true},{"inning_num":2,"runs":0,"dismissed":true},{"inning_num":3,"runs":10,"dismissed":false},{"inning_num":4,"runs":0,"dismissed":true},{"inning_num":5,"runs":5,"dismissed":true},{"inning_num":6,"runs":45,"dismissed":true},{"inning_num":7,"runs":3,"dismissed":true},{"inning_num":8,"runs":0,"dismissed":true},{"inning_num":9,"runs":24,"dismissed":false},{"inning_num":10,"runs":8,"dismissed":true},{"inning_num":11,"runs":8,"dismissed":true},{"inning_num":12,"runs":1,"dismissed":true},{"inning_num":13,"runs":21,"dismissed":true},{"inning_num":14,"runs":3,"dismissed":false},{"inning_num":15,"runs":7,"dismissed":true},{"inning_num":16,"runs":27,"dismissed":true},{"inning_num":17,"runs":22,"dismissed":false},{"inning_num":18,"runs":2,"dismissed":true},{"inning_num":19,"runs":8,"dismissed":true},{"inning_num":20,"runs":0,"dismissed":true},{"inning_num":21,"runs":1,"dismissed":true},{"inning_num":22,"runs":45,"dismissed":true},{"inning_num":23,"runs":5,"dismissed":false},{"inning_num":24,"runs":9,"dismissed":true},{"inning_num":25,"runs":16,"dismissed":true},{"inning_num":26,"runs":5,"dismissed":true},{"inning_num":27,"runs":1,"dismissed":false},{"inning_num":28,"runs":21,"dismissed":true},{"inning_num":29,"runs":46,"dismissed":true},{"inning_num":30,"runs":18,"dismissed":true},{"inning_num":31,"runs":0,"dismissed":true},{"inning_num":32,"runs":13,"dismissed":true},{"inning_num":33,"runs":0,"dismissed":true},{"inning_num":34,"runs":0,"dismissed":true},{"inning_num":35,"runs":18,"dismissed":true},{"inning_num":36,"runs":9,"dismissed":true},{"inning_num":37,"runs":13,"dismissed":true},{"inning_num":38,"runs":79,"dismissed":true},{"inning_num":39,"runs":36,"dismissed":true},{"inning_num":40,"runs":1,"dismissed":true},{"inning_num":41,"runs":45,"dismissed":true},{"inning_num":42,"runs":0,"dismissed":true},{"inning_num":43,"runs":11,"dismissed":true},{"inning_num":44,"runs":11,"dismissed":true},{"inning_num":45,"runs":32,"dismissed":true},{"inning_num":46,"runs":3,"dismissed":true},{"inning_num":47,"runs":16,"dismissed":false},{"inning_num":48,"runs":18,"dismissed":false},{"inning_num":49,"runs":43,"dismissed":true},{"inning_num":50,"runs":6,"dismissed":false},{"inning_num":51,"runs":27,"dismissed":true},{"inning_num":52,"runs":31,"dismissed":false},{"inning_num":53,"runs":58,"dismissed":false},{"inning_num":54,"runs":9,"dismissed":false},{"inning_num":55,"runs":51,"dismissed":true},{"inning_num":56,"runs":18,"dismissed":true},{"inning_num":57,"runs":11,"dismissed":false},{"inning_num":58,"runs":13,"dismissed":false}],"batting_seasons":[{"season":2015,"runs":26,"matches":5,"dismissals":4,"avg":6.5},{"season":2016,"runs":89,"matches":7,"dismissals":6,"avg":14.83},{"season":2018,"runs":21,"matches":1,"dismissals":1,"avg":21.0},{"season":2019,"runs":129,"matches":11,"dismissals":8,"avg":16.12},{"season":2020,"runs":120,"matches":9,"dismissals":8,"avg":15.0},{"season":2021,"runs":258,"matches":13,"dismissals":13,"avg":19.85},{"season":2025,"runs":301,"matches":12,"dismissals":5,"avg":60.2}],"bowling":{"wickets":36,"matches":40,"balls":480,"runs_conceded":704,"economy":8.8,"average":19.56},"bowling_seasons":[{"season":2015,"runs":121,"wickets":7,"balls":96,"matches":6,"economy":7.56},{"season":2016,"runs":141,"wickets":6,"balls":84,"matches":9,"economy":10.07},{"season":2018,"runs":28,"wickets":1,"balls":18,"matches":2,"economy":9.33},{"season":2019,"runs":174,"wickets":8,"balls":120,"matches":10,"economy":8.7},{"season":2020,"runs":78,"wickets":0,"balls":54,"matches":5,"economy":8.67},{"season":2021,"runs":162,"wickets":14,"balls":108,"matches":8,"economy":9.0}],"cais_batting":{"score":208.94,"rank":261,"total":401},"cais_bowling":{"score":27.66,"rank":157,"total":380}}