{"name":"MS Chapman","competition":"psl","batting":{"total_runs":158,"matches":7,"innings":7,"dismissals":5,"average":31.6,"sr":156.44,"highest":42,"fifties":0,"hundreds":0},"innings_list":[{"inning_num":1,"runs":4,"dismissed":true},{"inning_num":2,"runs":33,"dismissed":true},{"inning_num":3,"runs":2,"dismissed":true},{"inning_num":4,"runs":13,"dismissed":false},{"inning_num":5,"runs":40,"dismissed":true},{"inning_num":6,"runs":24,"dismissed":false},{"inning_num":7,"runs":42,"dismissed":true}],"batting_seasons":[{"season":2025,"runs":52,"matches":4,"dismissals":3,"avg":17.33},{"season":2026,"runs":106,"matches":3,"dismissals":2,"avg":53.0}]}