{"name":"MJ Guptill","competition":"ilt","batting":{"total_runs":122,"matches":6,"innings":6,"dismissals":5,"average":24.4,"sr":106.09,"highest":40,"fifties":0,"hundreds":0},"innings_list":[{"inning_num":1,"runs":40,"dismissed":true},{"inning_num":2,"runs":2,"dismissed":true},{"inning_num":3,"runs":17,"dismissed":true},{"inning_num":4,"runs":39,"dismissed":true},{"inning_num":5,"runs":13,"dismissed":false},{"inning_num":6,"runs":11,"dismissed":true}],"batting_seasons":[{"season":2023,"runs":122,"matches":6,"dismissals":5,"avg":24.4}]}