[{"batter":"JEC Franklin","team":"New Zealand","cais":345.15,"raw_sr":177.97,"runs":105,"balls":59,"matches":4,"rank":1},{"batter":"JH Kallis","team":"South Africa","cais":307.28,"raw_sr":145.24,"runs":61,"balls":42,"matches":1,"rank":2},{"batter":"TM Dilshan","team":"Sri Lanka","cais":305.64,"raw_sr":174.36,"runs":136,"balls":78,"matches":3,"rank":3},{"batter":"RE Levi","team":"South Africa","cais":300.47,"raw_sr":207.79,"runs":160,"balls":77,"matches":4,"rank":4},{"batter":"E Chigumbura","team":"Zimbabwe","cais":288.55,"raw_sr":158.16,"runs":155,"balls":98,"matches":6,"rank":5},{"batter":"MEK Hussey","team":"Australia","cais":278.89,"raw_sr":132.73,"runs":73,"balls":55,"matches":2,"rank":6},{"batter":"CD Barnwell","team":"West Indies","cais":259.61,"raw_sr":129.79,"runs":61,"balls":47,"matches":4,"rank":7},{"batter":"SR Watson","team":"Australia","cais":259.01,"raw_sr":160.68,"runs":188,"balls":117,"matches":5,"rank":8},{"batter":"CA Ingram","team":"South Africa","cais":256.57,"raw_sr":134.88,"runs":116,"balls":86,"matches":4,"rank":9},{"batter":"KS Williamson","team":"New Zealand","cais":249.31,"raw_sr":135.48,"runs":126,"balls":93,"matches":5,"rank":10},{"batter":"T Taibu","team":"Zimbabwe","cais":249.25,"raw_sr":118.64,"runs":70,"balls":59,"matches":3,"rank":11},{"batter":"BB McCullum","team":"New Zealand","cais":244.64,"raw_sr":144.0,"runs":252,"balls":175,"matches":7,"rank":12},{"batter":"DR Smith","team":"West Indies","cais":237.97,"raw_sr":151.95,"runs":117,"balls":77,"matches":4,"rank":13},{"batter":"JP Duminy","team":"South Africa","cais":233.86,"raw_sr":128.07,"runs":146,"balls":114,"matches":4,"rank":14},{"batter":"EJG Morgan","team":"England","cais":233.11,"raw_sr":137.63,"runs":128,"balls":93,"matches":5,"rank":15},{"batter":"SK Raina","team":"India","cais":231.02,"raw_sr":127.54,"runs":88,"balls":69,"matches":4,"rank":16},{"batter":"MJ Guptill","team":"New Zealand","cais":229.96,"raw_sr":142.45,"runs":349,"balls":245,"matches":6,"rank":17},{"batter":"BRM Taylor","team":"Zimbabwe","cais":227.12,"raw_sr":126.27,"runs":149,"balls":118,"matches":6,"rank":18},{"batter":"G Gambhir","team":"India","cais":225.81,"raw_sr":122.55,"runs":125,"balls":102,"matches":3,"rank":19},{"batter":"KP Pietersen","team":"England","cais":220.37,"raw_sr":136.57,"runs":239,"balls":175,"matches":6,"rank":20},{"batter":"MS Dhoni","team":"India","cais":219.92,"raw_sr":103.16,"runs":98,"balls":95,"matches":4,"rank":21},{"batter":"Shahid Afridi","team":"Pakistan","cais":213.33,"raw_sr":122.22,"runs":77,"balls":63,"matches":6,"rank":22},{"batter":"KC Sangakkara","team":"Sri Lanka","cais":213.28,"raw_sr":123.26,"runs":106,"balls":86,"matches":4,"rank":23},{"batter":"DP Hyatt","team":"West Indies","cais":212.94,"raw_sr":118.52,"runs":64,"balls":54,"matches":5,"rank":24},{"batter":"CJ Chibhabha","team":"Zimbabwe","cais":211.7,"raw_sr":128.74,"runs":112,"balls":87,"matches":4,"rank":25},{"batter":"CL White","team":"Australia","cais":206.79,"raw_sr":129.89,"runs":113,"balls":87,"matches":4,"rank":26},{"batter":"DPMD Jayawardene","team":"Sri Lanka","cais":198.75,"raw_sr":129.01,"runs":169,"balls":131,"matches":3,"rank":27},{"batter":"DA Warner","team":"Australia","cais":191.78,"raw_sr":124.03,"runs":160,"balls":129,"matches":8,"rank":28},{"batter":"GJ Bailey","team":"Australia","cais":189.42,"raw_sr":120.0,"runs":60,"balls":50,"matches":4,"rank":29},{"batter":"Misbah-ul-Haq","team":"Pakistan","cais":188.7,"raw_sr":98.05,"runs":151,"balls":154,"matches":7,"rank":30},{"batter":"Umar Akmal","team":"Pakistan","cais":187.78,"raw_sr":110.95,"runs":152,"balls":137,"matches":8,"rank":31},{"batter":"AM Rahane","team":"India","cais":186.91,"raw_sr":145.24,"runs":61,"balls":42,"matches":2,"rank":32},{"batter":"H Masakadza","team":"Zimbabwe","cais":186.68,"raw_sr":137.04,"runs":148,"balls":108,"matches":6,"rank":33},{"batter":"DM Bravo","team":"West Indies","cais":185.99,"raw_sr":108.51,"runs":102,"balls":94,"matches":4,"rank":34},{"batter":"RJ Nicol","team":"New Zealand","cais":184.71,"raw_sr":138.38,"runs":137,"balls":99,"matches":5,"rank":35},{"batter":"Mohammad Hafeez","team":"Pakistan","cais":181.29,"raw_sr":116.25,"runs":186,"balls":160,"matches":8,"rank":36},{"batter":"MS Wade","team":"Australia","cais":180.22,"raw_sr":124.53,"runs":132,"balls":106,"matches":5,"rank":37},{"batter":"LMP Simmons","team":"West Indies","cais":175.41,"raw_sr":125.97,"runs":97,"balls":77,"matches":3,"rank":38},{"batter":"DJ Hussey","team":"Australia","cais":175.02,"raw_sr":103.17,"runs":130,"balls":126,"matches":7,"rank":39},{"batter":"J Charles","team":"West Indies","cais":171.96,"raw_sr":113.46,"runs":118,"balls":104,"matches":4,"rank":40},{"batter":"JD Ryder","team":"New Zealand","cais":170.19,"raw_sr":126.15,"runs":82,"balls":65,"matches":2,"rank":41},{"batter":"Shoaib Malik","team":"Pakistan","cais":169.2,"raw_sr":108.96,"runs":73,"balls":67,"matches":6,"rank":42},{"batter":"JM Bairstow","team":"England","cais":166.89,"raw_sr":109.64,"runs":91,"balls":83,"matches":5,"rank":43},{"batter":"LD Chandimal","team":"Sri Lanka","cais":164.25,"raw_sr":121.21,"runs":80,"balls":66,"matches":3,"rank":44},{"batter":"V Kohli","team":"India","cais":163.6,"raw_sr":110.26,"runs":86,"balls":78,"matches":5,"rank":45},{"batter":"Asad Shafiq","team":"Pakistan","cais":161.36,"raw_sr":111.95,"runs":178,"balls":159,"matches":8,"rank":46},{"batter":"MN Samuels","team":"West Indies","cais":158.69,"raw_sr":101.56,"runs":130,"balls":128,"matches":6,"rank":47},{"batter":"SR Patel","team":"England","cais":157.18,"raw_sr":101.32,"runs":77,"balls":76,"matches":7,"rank":48},{"batter":"C Kieswetter","team":"England","cais":155.0,"raw_sr":111.56,"runs":164,"balls":147,"matches":8,"rank":49},{"batter":"RS Bopara","team":"England","cais":154.87,"raw_sr":89.26,"runs":108,"balls":121,"matches":7,"rank":50},{"batter":"AB de Villiers","team":"South Africa","cais":150.85,"raw_sr":100.0,"runs":76,"balls":76,"matches":3,"rank":51},{"batter":"HM Amla","team":"South Africa","cais":137.65,"raw_sr":119.23,"runs":62,"balls":52,"matches":5,"rank":52},{"batter":"AD Hales","team":"England","cais":125.34,"raw_sr":96.15,"runs":75,"balls":78,"matches":4,"rank":53}]