[{"batter":"BCJ Cutting","team":"Quetta Gladiators","cais":411.51,"raw_sr":189.61,"runs":146,"balls":77,"matches":7,"rank":1},{"batter":"BR Dunk","team":"Lahore Qalandars","cais":338.13,"raw_sr":186.01,"runs":266,"balls":143,"matches":7,"rank":2},{"batter":"Khurram Manzoor","team":"Quetta Gladiators","cais":318.29,"raw_sr":157.5,"runs":63,"balls":40,"matches":1,"rank":3},{"batter":"CAK Walton","team":"Karachi Kings","cais":310.19,"raw_sr":156.7,"runs":152,"balls":97,"matches":8,"rank":4},{"batter":"CA Lynn","team":"Lahore Qalandars","cais":306.24,"raw_sr":179.75,"runs":284,"balls":158,"matches":8,"rank":5},{"batter":"SR Patel","team":"Lahore Qalandars","cais":296.19,"raw_sr":155.68,"runs":137,"balls":88,"matches":6,"rank":6},{"batter":"Shahid Afridi","team":"Multan Sultans","cais":279.03,"raw_sr":167.31,"runs":87,"balls":52,"matches":5,"rank":7},{"batter":"RR Rossouw","team":"Multan Sultans","cais":275.88,"raw_sr":154.92,"runs":189,"balls":122,"matches":6,"rank":8},{"batter":"CA Ingram","team":"Islamabad United","cais":273.03,"raw_sr":150.36,"runs":206,"balls":137,"matches":9,"rank":9},{"batter":"L Gregory","team":"Peshawar Zalmi","cais":272.69,"raw_sr":161.9,"runs":68,"balls":42,"matches":4,"rank":10},{"batter":"LS Livingstone","team":"Peshawar Zalmi","cais":272.68,"raw_sr":150.0,"runs":108,"balls":72,"matches":7,"rank":11},{"batter":"Khushdil Shah","team":"Multan Sultans","cais":265.03,"raw_sr":147.06,"runs":175,"balls":119,"matches":8,"rank":12},{"batter":"Shadab Khan","team":"Islamabad United","cais":264.92,"raw_sr":159.39,"runs":263,"balls":165,"matches":8,"rank":13},{"batter":"AD Hales","team":"Karachi Kings","cais":261.38,"raw_sr":156.21,"runs":239,"balls":153,"matches":5,"rank":14},{"batter":"SR Watson","team":"Quetta Gladiators","cais":261.02,"raw_sr":157.32,"runs":247,"balls":157,"matches":9,"rank":15},{"batter":"Asif Ali","team":"Islamabad United","cais":254.99,"raw_sr":150.0,"runs":81,"balls":54,"matches":7,"rank":16},{"batter":"Haider Ali","team":"Peshawar Zalmi","cais":253.2,"raw_sr":158.28,"runs":239,"balls":151,"matches":9,"rank":17},{"batter":"Kamran Akmal","team":"Peshawar Zalmi","cais":241.87,"raw_sr":161.94,"runs":251,"balls":155,"matches":9,"rank":18},{"batter":"Imad Wasim","team":"Karachi Kings","cais":241.66,"raw_sr":127.37,"runs":121,"balls":95,"matches":5,"rank":19},{"batter":"Shoaib Malik","team":"Peshawar Zalmi","cais":241.23,"raw_sr":134.27,"runs":239,"balls":178,"matches":7,"rank":20},{"batter":"L Ronchi","team":"Islamabad United","cais":238.47,"raw_sr":156.47,"runs":266,"balls":170,"matches":8,"rank":21},{"batter":"JM Vince","team":"Multan Sultans","cais":238.01,"raw_sr":166.67,"runs":155,"balls":93,"matches":5,"rank":22},{"batter":"DJ Malan","team":"Islamabad United","cais":236.04,"raw_sr":142.39,"runs":131,"balls":92,"matches":4,"rank":23},{"batter":"Shan Masood","team":"Multan Sultans","cais":232.33,"raw_sr":128.43,"runs":253,"balls":197,"matches":8,"rank":24},{"batter":"CS Delport","team":"Karachi Kings","cais":226.75,"raw_sr":121.09,"runs":178,"balls":147,"matches":8,"rank":25},{"batter":"Azam Khan","team":"Quetta Gladiators","cais":223.02,"raw_sr":130.43,"runs":150,"balls":115,"matches":9,"rank":26},{"batter":"Imam-ul-Haq","team":"Peshawar Zalmi","cais":222.08,"raw_sr":122.81,"runs":70,"balls":57,"matches":3,"rank":27},{"batter":"C Munro","team":"Islamabad United","cais":219.29,"raw_sr":147.62,"runs":248,"balls":168,"matches":8,"rank":28},{"batter":"Sharjeel Khan","team":"Karachi Kings","cais":215.73,"raw_sr":144.2,"runs":199,"balls":138,"matches":9,"rank":29},{"batter":"Fakhar Zaman","team":"Lahore Qalandars","cais":212.72,"raw_sr":132.97,"runs":246,"balls":185,"matches":9,"rank":30},{"batter":"Sohail Akhtar","team":"Lahore Qalandars","cais":212.1,"raw_sr":122.92,"runs":236,"balls":192,"matches":9,"rank":31},{"batter":"Iftikhar Ahmed","team":"Karachi Kings","cais":211.98,"raw_sr":129.51,"runs":79,"balls":61,"matches":7,"rank":32},{"batter":"Babar Azam","team":"Karachi Kings","cais":210.8,"raw_sr":123.66,"runs":345,"balls":279,"matches":8,"rank":33},{"batter":"Sarfraz Ahmed","team":"Quetta Gladiators","cais":205.84,"raw_sr":128.7,"runs":148,"balls":115,"matches":9,"rank":34},{"batter":"Mohammad Hafeez","team":"Lahore Qalandars","cais":201.97,"raw_sr":121.91,"runs":217,"balls":178,"matches":9,"rank":35},{"batter":"Zeeshan Ashraf","team":"Multan Sultans","cais":199.23,"raw_sr":133.07,"runs":169,"balls":127,"matches":9,"rank":36},{"batter":"Mohammad Nawaz (3)","team":"Quetta Gladiators","cais":196.47,"raw_sr":116.0,"runs":116,"balls":100,"matches":9,"rank":37},{"batter":"JJ Roy","team":"Quetta Gladiators","cais":188.02,"raw_sr":120.1,"runs":233,"balls":194,"matches":8,"rank":38},{"batter":"Hussain Talat","team":"Islamabad United","cais":186.53,"raw_sr":103.39,"runs":61,"balls":59,"matches":3,"rank":39},{"batter":"MM Ali","team":"Multan Sultans","cais":177.03,"raw_sr":130.19,"runs":138,"balls":106,"matches":9,"rank":40},{"batter":"T Banton","team":"Peshawar Zalmi","cais":156.14,"raw_sr":129.82,"runs":74,"balls":57,"matches":7,"rank":41},{"batter":"Sohail Khan","team":"Quetta Gladiators","cais":149.27,"raw_sr":108.33,"runs":65,"balls":60,"matches":5,"rank":42},{"batter":"Ahmed Shehzad","team":"Quetta Gladiators","cais":144.07,"raw_sr":95.31,"runs":61,"balls":64,"matches":7,"rank":43}]