{"name":"IS Sodhi","competition":"wc","batting":{"total_runs":9,"matches":3,"innings":3,"dismissals":1,"average":9.0,"sr":100.0,"highest":6,"fifties":0,"hundreds":0},"innings_list":[{"inning_num":1,"runs":2,"dismissed":false},{"inning_num":2,"runs":1,"dismissed":true},{"inning_num":3,"runs":6,"dismissed":false}],"batting_seasons":[{"season":2021,"runs":2,"matches":1,"dismissals":0,"avg":NaN},{"season":2022,"runs":7,"matches":2,"dismissals":1,"avg":7.0}],"bowling":{"wickets":26,"matches":19,"balls":412,"runs_conceded":476,"economy":6.93,"average":18.31},"bowling_seasons":[{"season":2016,"runs":118,"wickets":10,"balls":118,"matches":5,"economy":6.0},{"season":2021,"runs":169,"wickets":8,"balls":132,"matches":6,"economy":7.68},{"season":2022,"runs":127,"wickets":6,"balls":116,"matches":5,"economy":6.57},{"season":2024,"runs":28,"wickets":2,"balls":22,"matches":1,"economy":7.64},{"season":2026,"runs":34,"wickets":0,"balls":24,"matches":2,"economy":8.5}],"cais_bowling":{"score":23.24,"rank":80,"total":137}}