[{"batter":"R Powell","team":"Kandy Warriors","cais":409.5,"raw_sr":236.36,"runs":104,"balls":44,"matches":3,"runs_pp":0,"runs_mid":101,"runs_death":3,"balls_pp":0,"balls_mid":37,"balls_death":7,"bonus_pressure":15.87,"bonus_stage":0.0,"bonus_opponent":0.0,"form_avg":1.3,"rank":1},{"batter":"NLTC Perera","team":"Jaffna Kings","cais":344.44,"raw_sr":190.0,"runs":190,"balls":100,"matches":9,"runs_pp":7,"runs_mid":105,"runs_death":78,"balls_pp":5,"balls_mid":61,"balls_death":34,"bonus_pressure":12.616,"bonus_stage":8.2,"bonus_opponent":0.0,"form_avg":1.3287,"rank":2},{"batter":"LD Chandimal","team":"Colombo Stars","cais":317.15,"raw_sr":150.54,"runs":277,"balls":184,"matches":9,"runs_pp":8,"runs_mid":116,"runs_death":153,"balls_pp":7,"balls_mid":103,"balls_death":74,"bonus_pressure":50.538,"bonus_stage":4.8,"bonus_opponent":0.0,"form_avg":1.3998,"rank":3},{"batter":"PWH de Silva","team":"Jaffna Kings","cais":293.34,"raw_sr":185.42,"runs":89,"balls":48,"matches":6,"runs_pp":37,"runs_mid":29,"runs_death":23,"balls_pp":18,"balls_mid":16,"balls_death":14,"bonus_pressure":10.987,"bonus_stage":5.8,"bonus_opponent":0.0,"form_avg":1.165,"rank":4},{"batter":"S Prasanna","team":"Colombo Stars","cais":289.15,"raw_sr":154.9,"runs":79,"balls":51,"matches":8,"runs_pp":0,"runs_mid":14,"runs_death":65,"balls_pp":0,"balls_mid":17,"balls_death":34,"bonus_pressure":19.006,"bonus_stage":1.5,"bonus_opponent":0.0,"form_avg":1.1258,"rank":5},{"batter":"Shoaib Malik","team":"Jaffna Kings","cais":277.42,"raw_sr":151.85,"runs":164,"balls":108,"matches":9,"runs_pp":22,"runs_mid":105,"runs_death":37,"balls_pp":19,"balls_mid":70,"balls_death":19,"bonus_pressure":9.577,"bonus_stage":10.8,"bonus_opponent":0.0,"form_avg":1.3823,"rank":6},{"batter":"C Karunaratne","team":"Dambulla Giants","cais":271.82,"raw_sr":133.33,"runs":156,"balls":117,"matches":10,"runs_pp":0,"runs_mid":38,"runs_death":118,"balls_pp":0,"balls_mid":52,"balls_death":65,"bonus_pressure":35.701,"bonus_stage":17.0,"bonus_opponent":0.0,"form_avg":1.137,"rank":7},{"batter":"WIA Fernando","team":"Jaffna Kings","cais":268.32,"raw_sr":152.94,"runs":312,"balls":204,"matches":10,"runs_pp":170,"runs_mid":102,"runs_death":40,"balls_pp":111,"balls_mid":75,"balls_death":18,"bonus_pressure":8.178,"bonus_stage":40.8,"bonus_opponent":0.0,"form_avg":1.4133,"rank":8},{"batter":"RTM Mendis","team":"Dambulla Giants","cais":255.54,"raw_sr":134.41,"runs":125,"balls":93,"matches":8,"runs_pp":5,"runs_mid":25,"runs_death":95,"balls_pp":4,"balls_mid":28,"balls_death":61,"bonus_pressure":9.69,"bonus_stage":0.0,"bonus_opponent":0.0,"form_avg":1.3648,"rank":9},{"batter":"BKG Mendis","team":"Galle Gladiators","cais":248.37,"raw_sr":148.64,"runs":327,"balls":220,"matches":10,"runs_pp":183,"runs_mid":130,"runs_death":14,"balls_pp":113,"balls_mid":99,"balls_death":8,"bonus_pressure":11.74,"bonus_stage":29.6,"bonus_opponent":0.0,"form_avg":1.4048,"rank":10},{"batter":"PBB Rajapaksa","team":"Galle Gladiators","cais":245.04,"raw_sr":134.59,"runs":179,"balls":133,"matches":9,"runs_pp":11,"runs_mid":121,"runs_death":47,"balls_pp":9,"balls_mid":98,"balls_death":26,"bonus_pressure":10.409,"bonus_stage":11.5,"bonus_opponent":0.0,"form_avg":1.3553,"rank":11},{"batter":"AD Mathews","team":"Colombo Stars","cais":236.04,"raw_sr":128.19,"runs":191,"balls":149,"matches":5,"runs_pp":43,"runs_mid":91,"runs_death":57,"balls_pp":41,"balls_mid":76,"balls_death":32,"bonus_pressure":10.189,"bonus_stage":12.9,"bonus_opponent":0.0,"form_avg":1.3974,"rank":12},{"batter":"PD Salt","team":"Dambulla Giants","cais":232.83,"raw_sr":154.36,"runs":301,"balls":195,"matches":10,"runs_pp":230,"runs_mid":71,"runs_death":0,"balls_pp":143,"balls_mid":52,"balls_death":0,"bonus_pressure":11.598,"bonus_stage":10.8,"bonus_opponent":0.0,"form_avg":1.405,"rank":13},{"batter":"T Kohler-Cadmore","team":"Jaffna Kings","cais":225.54,"raw_sr":137.04,"runs":296,"balls":216,"matches":11,"runs_pp":118,"runs_mid":148,"runs_death":30,"balls_pp":85,"balls_mid":110,"balls_death":21,"bonus_pressure":11.119,"bonus_stage":21.6,"bonus_opponent":0.0,"form_avg":1.3489,"rank":14},{"batter":"Rahmanullah Gurbaz","team":"Jaffna Kings","cais":223.9,"raw_sr":144.76,"runs":207,"balls":143,"matches":8,"runs_pp":123,"runs_mid":84,"runs_death":0,"balls_pp":98,"balls_mid":45,"balls_death":0,"bonus_pressure":10.728,"bonus_stage":38.4,"bonus_opponent":0.0,"form_avg":1.2005,"rank":15},{"batter":"SR Patel","team":"Galle Gladiators","cais":222.42,"raw_sr":111.29,"runs":138,"balls":124,"matches":8,"runs_pp":1,"runs_mid":65,"runs_death":72,"balls_pp":1,"balls_mid":79,"balls_death":44,"bonus_pressure":13.333,"bonus_stage":6.7,"bonus_opponent":0.0,"form_avg":1.3739,"rank":16},{"batter":"N Dickwella","team":"Dambulla Giants","cais":206.42,"raw_sr":152.53,"runs":151,"balls":99,"matches":10,"runs_pp":137,"runs_mid":14,"runs_death":0,"balls_pp":87,"balls_mid":12,"balls_death":0,"bonus_pressure":3.948,"bonus_stage":3.6,"bonus_opponent":0.0,"form_avg":1.3285,"rank":17},{"batter":"J Liyanage","team":"Dambulla Giants","cais":203.48,"raw_sr":120.0,"runs":108,"balls":90,"matches":4,"runs_pp":44,"runs_mid":54,"runs_death":10,"balls_pp":36,"balls_mid":47,"balls_death":7,"bonus_pressure":5.431,"bonus_stage":11.4,"bonus_opponent":0.0,"form_avg":1.3375,"rank":18},{"batter":"SMA Priyanjan","team":"Colombo Stars","cais":200.16,"raw_sr":116.92,"runs":76,"balls":65,"matches":6,"runs_pp":23,"runs_mid":53,"runs_death":0,"balls_pp":28,"balls_mid":37,"balls_death":0,"bonus_pressure":11.495,"bonus_stage":0.0,"bonus_opponent":0.0,"form_avg":1.3642,"rank":19},{"batter":"KNA Bandara","team":"Jaffna Kings","cais":197.4,"raw_sr":113.64,"runs":75,"balls":66,"matches":5,"runs_pp":5,"runs_mid":51,"runs_death":19,"balls_pp":11,"balls_mid":45,"balls_death":10,"bonus_pressure":7.006,"bonus_stage":3.6,"bonus_opponent":0.0,"form_avg":1.2717,"rank":20},{"batter":"MD Shanaka","team":"Dambulla Giants","cais":195.54,"raw_sr":113.93,"runs":139,"balls":122,"matches":8,"runs_pp":16,"runs_mid":85,"runs_death":38,"balls_pp":18,"balls_mid":75,"balls_death":29,"bonus_pressure":9.041,"bonus_stage":0.0,"bonus_opponent":0.0,"form_avg":1.3659,"rank":21},{"batter":"KIC Asalanka","team":"Kandy Warriors","cais":195.44,"raw_sr":137.82,"runs":164,"balls":119,"matches":8,"runs_pp":114,"runs_mid":50,"runs_death":0,"balls_pp":82,"balls_mid":37,"balls_death":0,"bonus_pressure":4.859,"bonus_stage":1.4,"bonus_opponent":0.0,"form_avg":1.3488,"rank":22},{"batter":"DM de Silva","team":"Colombo Stars","cais":192.27,"raw_sr":114.84,"runs":147,"balls":128,"matches":8,"runs_pp":65,"runs_mid":80,"runs_death":2,"balls_pp":56,"balls_mid":70,"balls_death":2,"bonus_pressure":15.7,"bonus_stage":7.0,"bonus_opponent":0.0,"form_avg":1.3582,"rank":23},{"batter":"MD Gunathilaka","team":"Galle Gladiators","cais":191.63,"raw_sr":129.89,"runs":226,"balls":174,"matches":10,"runs_pp":182,"runs_mid":44,"runs_death":0,"balls_pp":121,"balls_mid":53,"balls_death":0,"bonus_pressure":3.983,"bonus_stage":29.1,"bonus_opponent":0.0,"form_avg":1.2968,"rank":24},{"batter":"Najibullah Zadran","team":"Dambulla Giants","cais":191.22,"raw_sr":112.59,"runs":152,"balls":135,"matches":9,"runs_pp":4,"runs_mid":122,"runs_death":26,"balls_pp":8,"balls_mid":103,"balls_death":24,"bonus_pressure":12.44,"bonus_stage":11.0,"bonus_opponent":0.0,"form_avg":1.2417,"rank":25},{"batter":"RS Bopara","team":"Kandy Warriors","cais":191.07,"raw_sr":113.6,"runs":142,"balls":125,"matches":4,"runs_pp":36,"runs_mid":76,"runs_death":30,"balls_pp":27,"balls_mid":73,"balls_death":25,"bonus_pressure":10.825,"bonus_stage":4.7,"bonus_opponent":0.0,"form_avg":1.3297,"rank":26},{"batter":"MDKJ Perera","team":"Colombo Stars","cais":182.8,"raw_sr":129.73,"runs":96,"balls":74,"matches":7,"runs_pp":64,"runs_mid":32,"runs_death":0,"balls_pp":50,"balls_mid":24,"balls_death":0,"bonus_pressure":5.985,"bonus_stage":6.4,"bonus_opponent":0.0,"form_avg":1.2235,"rank":27},{"batter":"K Lewis","team":"Kandy Warriors","cais":178.46,"raw_sr":130.23,"runs":168,"balls":129,"matches":6,"runs_pp":121,"runs_mid":47,"runs_death":0,"balls_pp":88,"balls_mid":41,"balls_death":0,"bonus_pressure":4.729,"bonus_stage":2.1,"bonus_opponent":0.0,"form_avg":1.3093,"rank":28},{"batter":"BR Dunk","team":"Galle Gladiators","cais":174.42,"raw_sr":112.9,"runs":70,"balls":62,"matches":5,"runs_pp":26,"runs_mid":44,"runs_death":0,"balls_pp":24,"balls_mid":38,"balls_death":0,"bonus_pressure":5.123,"bonus_stage":0.0,"bonus_opponent":0.0,"form_avg":1.3391,"rank":29},{"batter":"AK Perera","team":"Kandy Warriors","cais":168.56,"raw_sr":108.33,"runs":78,"balls":72,"matches":7,"runs_pp":30,"runs_mid":22,"runs_death":26,"balls_pp":23,"balls_mid":31,"balls_death":18,"bonus_pressure":7.374,"bonus_stage":0.0,"bonus_opponent":0.0,"form_avg":1.2547,"rank":30},{"batter":"T Banton","team":"Colombo Stars","cais":155.43,"raw_sr":107.92,"runs":109,"balls":101,"matches":8,"runs_pp":84,"runs_mid":25,"runs_death":0,"balls_pp":67,"balls_mid":34,"balls_death":0,"bonus_pressure":13.658,"bonus_stage":2.8,"bonus_opponent":0.0,"form_avg":1.2513,"rank":31},{"batter":"PHKD Mendis","team":"Kandy Warriors","cais":150.07,"raw_sr":93.62,"runs":88,"balls":94,"matches":7,"runs_pp":14,"runs_mid":70,"runs_death":4,"balls_pp":15,"balls_mid":71,"balls_death":8,"bonus_pressure":8.602,"bonus_stage":1.3,"bonus_opponent":0.0,"form_avg":1.2743,"rank":32},{"batter":"Ahmed Shehzad","team":"Kandy Warriors","cais":144.27,"raw_sr":103.9,"runs":80,"balls":77,"matches":3,"runs_pp":53,"runs_mid":26,"runs_death":1,"balls_pp":38,"balls_mid":36,"balls_death":3,"bonus_pressure":3.815,"bonus_stage":0.0,"bonus_opponent":0.0,"form_avg":1.3,"rank":33},{"batter":"WU Tharanga","team":"Jaffna Kings","cais":143.37,"raw_sr":109.52,"runs":69,"balls":63,"matches":4,"runs_pp":57,"runs_mid":12,"runs_death":0,"balls_pp":50,"balls_mid":13,"balls_death":0,"bonus_pressure":0.144,"bonus_stage":0.0,"bonus_opponent":0.0,"form_avg":1.3266,"rank":34},{"batter":"Mohammad Hafeez","team":"Galle Gladiators","cais":123.87,"raw_sr":89.9,"runs":89,"balls":99,"matches":8,"runs_pp":56,"runs_mid":32,"runs_death":1,"balls_pp":59,"balls_mid":37,"balls_death":3,"bonus_pressure":4.826,"bonus_stage":4.7,"bonus_opponent":0.0,"form_avg":1.2131,"rank":35}]