{"name":"Rehan Ahmed","competition":"hnd","batting":{"total_runs":234,"matches":15,"innings":15,"dismissals":10,"average":23.4,"sr":123.81,"highest":45,"fifties":0,"hundreds":0},"innings_list":[{"inning_num":1,"runs":1,"dismissed":false},{"inning_num":2,"runs":33,"dismissed":true},{"inning_num":3,"runs":1,"dismissed":false},{"inning_num":4,"runs":1,"dismissed":false},{"inning_num":5,"runs":1,"dismissed":false},{"inning_num":6,"runs":8,"dismissed":true},{"inning_num":7,"runs":25,"dismissed":true},{"inning_num":8,"runs":31,"dismissed":true},{"inning_num":9,"runs":0,"dismissed":true},{"inning_num":10,"runs":13,"dismissed":true},{"inning_num":11,"runs":45,"dismissed":false},{"inning_num":12,"runs":28,"dismissed":true},{"inning_num":13,"runs":10,"dismissed":true},{"inning_num":14,"runs":37,"dismissed":true},{"inning_num":15,"runs":0,"dismissed":true}],"batting_seasons":[{"season":2022,"runs":34,"matches":2,"dismissals":1,"avg":34.0},{"season":2023,"runs":3,"matches":3,"dismissals":0,"avg":NaN},{"season":2024,"runs":8,"matches":1,"dismissals":1,"avg":8.0},{"season":2025,"runs":189,"matches":9,"dismissals":8,"avg":23.62}],"bowling":{"wickets":22,"matches":25,"balls":412,"runs_conceded":520,"economy":7.57,"average":23.64},"bowling_seasons":[{"season":2022,"runs":91,"wickets":2,"balls":72,"matches":5,"economy":7.58},{"season":2023,"runs":172,"wickets":8,"balls":150,"matches":8,"economy":6.88},{"season":2024,"runs":72,"wickets":0,"balls":40,"matches":2,"economy":10.8},{"season":2025,"runs":185,"wickets":12,"balls":150,"matches":10,"economy":7.4}],"cais_batting":{"score":197.57,"rank":66,"total":74},"cais_bowling":{"score":22.6,"rank":58,"total":73}}